[
  {
    "ContainingType": "ProdutosApp.Controllers.CategoriasController",
    "Method": "Get",
    "RelativePath": "api/Categorias",
    "HttpMethod": "GET",
    "IsController": true,
    "Order": 0,
    "Parameters": [],
    "ReturnTypes": []
  },
  {
    "ContainingType": "ProdutosApp.Controllers.ProdutosController",
    "Method": "Post",
    "RelativePath": "api/Produtos",
    "HttpMethod": "POST",
    "IsController": true,
    "Order": 0,
    "Parameters": [],
    "ReturnTypes": []
  },
  {
    "ContainingType": "ProdutosApp.Controllers.ProdutosController",
    "Method": "Put",
    "RelativePath": "api/Produtos",
    "HttpMethod": "PUT",
    "IsController": true,
    "Order": 0,
    "Parameters": [],
    "ReturnTypes": []
  },
  {
    "ContainingType": "ProdutosApp.Controllers.ProdutosController",
    "Method": "Delete",
    "RelativePath": "api/Produtos",
    "HttpMethod": "DELETE",
    "IsController": true,
    "Order": 0,
    "Parameters": [],
    "ReturnTypes": []
  },
  {
    "ContainingType": "ProdutosApp.Controllers.ProdutosController",
    "Method": "Get",
    "RelativePath": "api/Produtos",
    "HttpMethod": "GET",
    "IsController": true,
    "Order": 0,
    "Parameters": [],
    "ReturnTypes": []
  }
]